links_demo.py
links_demo-0.7.dist-info/LICENSE
links_demo-0.7.dist-info/WHEEL
links_demo-0.7.dist-info/METADATA
links_demo-0.7.dist-info/RECORD
