Metadata-Version: 2.1
Name: links-demo
Version: 0.7
Summary: Sample package for testing PyPI links.
Author-email: Patrick Arminio <patrick.arminio@gmail.com>
Classifier: License :: OSI Approved :: MIT License
Project-URL: AppVeyor, https://ci.appveyor.com/project/example
Project-URL: Bitbucket, https://bitbucket.org/example
Project-URL: Changelog, https://example.com/
Project-URL: CircleCI, https://circleci.com/example
Project-URL: Codecov, https://codecov.io/example
Project-URL: Coveralls, https://coveralls.io/example
Project-URL: Discord, https://discord.gg/example
Project-URL: Documentation, https://example.com/
Project-URL: Download, https://example.com/
Project-URL: GitLab, https://gitlab.com/example
Project-URL: Gitter, https://gitter.im/example
Project-URL: Google, https://google.com/example
Project-URL: Homepage, https://example.com/
Project-URL: Issues, https://example.com/
Project-URL: Mastodon, https://example.com/@example
Project-URL: PyPI, https://pypi.org/project/links-demo
Project-URL: Python, https://www.python.org/example
Project-URL: Reddit, https://www.reddit.com/r/example
Project-URL: Slack, https://something.slack.com/example
Project-URL: Source, https://github.com/patrick91/links-demo
Project-URL: Sponsor, https://example.com/
Project-URL: Twitter, https://twitter.com/example
Project-URL: YouTube, https://www.youtube.com/example
